MANIFEST.in
README.md
setup.py
pthread_event/__init__.py
pthread_event/_pthread_event.c
pthread_event/interruptible_event.py
pthread_event.egg-info/PKG-INFO
pthread_event.egg-info/SOURCES.txt
pthread_event.egg-info/dependency_links.txt
pthread_event.egg-info/top_level.txt
pthread_event/tests/__init__.py
pthread_event/tests/test_test_event.py