Metadata-Version: 1.1
Name: pthread-event
Version: 0.2
Summary: Event using pthread lock API
Home-page: https://github.com/stephan-hof/pthread_event
Author: Stephan Hofmockel
Author-email: Use the github issues
License: boost
Keywords: event pthread
Platform: UNKNOWN
Classifier: Programming Language :: C
Classifier: Intended Audience :: Developers
Classifier: Programming Language :: Python :: 2.6
Classifier: Programming Language :: Python :: 2.7
Classifier: Operating System :: POSIX
